metrics2mqtt/base.py
metrics2mqtt/metrics.py
metrics2mqtt-0.1.18.dist-info/LICENSE
metrics2mqtt-0.1.18.dist-info/METADATA
metrics2mqtt-0.1.18.dist-info/WHEEL
metrics2mqtt-0.1.18.dist-info/entry_points.txt
metrics2mqtt-0.1.18.dist-info/top_level.txt
metrics2mqtt-0.1.18.dist-info/RECORD
