Metadata-Version: 2.1
Name: metrics2mqtt
Version: 0.1.18
Summary: Publish cross-platorm system performance metrics to a MQTT broker
Home-page: https://github.com/jamiebegin/metrics2mqtt
Author: UNKNOWN
Author-email: jjbegin@gmail.com
License: MIT
Download-URL: https://github.com/jamiebegin/metrics2mqtt/archive/v0.1.18.tar.gz
Keywords: mqtt,psutil,metrics
Platform: UNKNOWN
Classifier: Development Status :: 3 - Alpha
Classifier: Intended Audience :: Information Technology
Classifier: Topic :: System :: Monitoring
Classifier: Topic :: System :: Logging
Classifier: Topic :: System :: Systems Administration
Classifier: License :: OSI Approved :: MIT License
Classifier: Programming Language :: Python :: 3.6
Classifier: Programming Language :: Python :: 3.7
Requires-Dist: jsons
Requires-Dist: psutil
Requires-Dist: paho-mqtt
Requires-Dist: numpy
